{
    "compos": [
        {
            "class": "Background",
            "column_max": 450,
            "height": 800,
            "row_max": 800,
            "width": 450,
            "column_min": 0,
            "row_min": 0,
            "id": 0
        },
        {
            "class": "Compo",
            "column_max": 46,
            "height": 20,
            "row_max": 67,
            "width": 27,
            "column_min": 19,
            "row_min": 47,
            "id": 1
        },
        {
            "class": "Compo",
            "column_max": 319,
            "height": 21,
            "row_max": 67,
            "width": 193,
            "column_min": 126,
            "row_min": 46,
            "id": 2
        },
        {
            "class": "Compo",
            "column_max": 306,
            "height": 20,
            "row_max": 340,
            "width": 167,
            "column_min": 139,
            "row_min": 320,
            "id": 3
        },
        {
            "class": "Compo",
            "column_max": 366,
            "height": 40,
            "row_max": 407,
            "width": 281,
            "column_min": 85,
            "row_min": 367,
            "id": 4
        },
        {
            "class": "Compo",
            "column_max": 273,
            "height": 27,
            "row_max": 454,
            "width": 94,
            "column_min": 179,
            "row_min": 427,
            "id": 5
        },
        {
            "class": "Compo",
            "column_max": 366,
            "height": 20,
            "row_max": 700,
            "width": 286,
            "column_min": 80,
            "row_min": 680,
            "id": 6
        },
        {
            "class": "Block",
            "column_max": 260,
            "height": 69,
            "row_max": 286,
            "width": 69,
            "column_min": 191,
            "row_min": 217,
            "id": 7
        },
        {
            "class": "Compo",
            "column_max": 259,
            "height": 60,
            "row_max": 280,
            "width": 66,
            "column_min": 193,
            "row_min": 220,
            "id": 8
        },
        {
            "class": "Block",
            "column_max": 333,
            "height": 40,
            "row_max": 640,
            "width": 217,
            "column_min": 116,
            "row_min": 600,
            "id": 9
        },
        {
            "class": "Compo",
            "column_max": 259,
            "height": 14,
            "row_max": 627,
            "width": 67,
            "column_min": 192,
            "row_min": 613,
            "id": 10
        }
    ]
}